immortal-0.2.dist-info/top_level.txt
immortal-0.2.dist-info/METADATA
immortal-0.2.dist-info/RECORD
immortal-0.2.dist-info/WHEEL
immortal/immortal_c.c
immortal/py.typed
immortal/__init__.py
immortal/immortal_c.cpython-312-x86_64-linux-gnu.so
